corut_qt/Qt5.py
corut_qt/__init__.py
corut_qt-0.0.4.dist-info/LICENSE
corut_qt-0.0.4.dist-info/METADATA
corut_qt-0.0.4.dist-info/WHEEL
corut_qt-0.0.4.dist-info/top_level.txt
corut_qt-0.0.4.dist-info/RECORD
