Metadata-Version: 2.1
Name: corut-qt
Version: 0.0.4
Summary: Advanced facilitating functions and Classes for QT
Home-page: https://pypi.org/project/corut_qt/
Author: ibrahim CÖRÜT
Author-email: ibrhmcorut@gmail.com
License: MIT License
Project-URL: Documentation, https://pypi.org/project/corut_qt/
Project-URL: Source Code, https://pypi.org/project/corut_qt/
Keywords: cörüt, corut, corut_qt, pyqt5
Platform: UNKNOWN
Classifier: Intended Audience :: Developers
Classifier: License :: OSI Approved :: MIT License
Classifier: Operating System :: OS Independent
Classifier: Programming Language :: Python :: 3
Classifier: Programming Language :: Python :: 3 :: Only
Classifier: Programming Language :: Python :: 3.7
Classifier: Programming Language :: Python :: 3.8
Classifier: Programming Language :: Python :: 3.9
Requires-Python: >=3.7
License-File: LICENSE
Requires-Dist: importlib-metadata
Requires-Dist: pyqt5
